{
  "content": [
    {
      "content": null,
      "created": "2022-05-29T20:53:24.268111Z",
      "format": null,
      "last_modified": "2022-05-29T20:53:24.268111Z",
      "mimetype": null,
      "name": "three-failed-saves-195436",
      "path": "stack-exchange/three-failed-saves-195436",
      "size": null,
      "type": "directory",
      "writable": true
    },
    {
      "content": null,
      "created": "2022-05-29T20:53:24.260111Z",
      "format": null,
      "last_modified": "2022-05-29T20:53:24.260111Z",
      "mimetype": null,
      "name": "charges-193353",
      "path": "stack-exchange/charges-193353",
      "size": null,
      "type": "directory",
      "writable": true
    },
    {
      "content": null,
      "created": "2022-05-29T20:53:24.260111Z",
      "format": null,
      "last_modified": "2022-05-29T20:53:24.260111Z",
      "mimetype": null,
      "name": "action-stress-198555",
      "path": "stack-exchange/action-stress-198555",
      "size": null,
      "type": "directory",
      "writable": true
    },
    {
      "content": null,
      "created": "2022-05-29T20:53:24.268111Z",
      "format": null,
      "last_modified": "2022-05-29T20:53:24.268111Z",
      "mimetype": null,
      "name": "uniform-successes-for-xdy-198566",
      "path": "stack-exchange/uniform-successes-for-xdy-198566",
      "size": null,
      "type": "directory",
      "writable": true
    },
    {
      "content": null,
      "created": "2022-05-29T20:53:24.268111Z",
      "format": null,
      "last_modified": "2022-05-29T20:53:24.268111Z",
      "mimetype": null,
      "name": "sum-of-highest-195988",
      "path": "stack-exchange/sum-of-highest-195988",
      "size": null,
      "type": "directory",
      "writable": true
    },
    {
      "content": null,
      "created": "2022-05-29T20:53:24.260111Z",
      "format": null,
      "last_modified": "2022-05-29T20:53:24.260111Z",
      "mimetype": null,
      "name": "dpr-195490",
      "path": "stack-exchange/dpr-195490",
      "size": null,
      "type": "directory",
      "writable": true
    },
    {
      "content": null,
      "created": "2022-05-29T20:53:24.268111Z",
      "format": null,
      "last_modified": "2022-05-29T20:53:24.268111Z",
      "mimetype": null,
      "name": "neon-city-overdrive-171498",
      "path": "stack-exchange/neon-city-overdrive-171498",
      "size": null,
      "type": "directory",
      "writable": true
    }
  ],
  "created": "2022-05-29T20:53:24.268111Z",
  "format": "json",
  "last_modified": "2022-05-29T20:53:24.268111Z",
  "mimetype": null,
  "name": "stack-exchange",
  "path": "stack-exchange",
  "size": null,
  "type": "directory",
  "writable": true
}